README.md
setup.py
port/__init__.py
port/_inputs.py
port/_utilities.py
port/action.py
port/blueprint.py
port/entity.py
port/outputs.py
port/provider.py
port-labs/__init__.py
port-labs/_inputs.py
port-labs/_utilities.py
port-labs/action.py
port-labs/blueprint.py
port-labs/entity.py
port-labs/outputs.py
port-labs/provider.py
port-labs/pulumi-plugin.json
port-labs/py.typed
port-labs/config/__init__.py
port-labs/config/vars.py
port/config/__init__.py
port/config/vars.py
port_labs.egg-info/PKG-INFO
port_labs.egg-info/SOURCES.txt
port_labs.egg-info/dependency_links.txt
port_labs.egg-info/not-zip-safe
port_labs.egg-info/requires.txt
port_labs.egg-info/top_level.txt