Metadata-Version: 2.1
Name: port-labs
Version: 0.0.10
Summary: A Pulumi package for creating and managing Port resources.
Home-page: https://www.pulumi.com
License: Apache-2.0
Project-URL: Repository, https://github.com/port-labs/pulumi-port-labs
Keywords: pulumi port category/utility
Platform: UNKNOWN
